{
    "records": [
        {
            "attributes": {
                "type": "eqAnswer__c",
                "referenceId": "eqAnswer__cRef1"
            },
            "Answer__c": "マネージャが所有するアカウント(取引先)とオポチュニティ(商談)に関するレポートをアクティブ化",
            "isAnswer__c": false,
            "eqQuestion__c": "@eqQuestion__cRef1"
        },
        {
            "attributes": {
                "type": "eqAnswer__c",
                "referenceId": "eqAnswer__cRef2"
            },
            "Answer__c": "マネージャが所有するアカウント(取引先)とコンタクト(取引先責任者)およびオポチュニティ(商談)に関する活動レポート",
            "isAnswer__c": true,
            "eqQuestion__c": "@eqQuestion__cRef1"
        },
        {
            "attributes": {
                "type": "eqAnswer__c",
                "referenceId": "eqAnswer__cRef3"
            },
            "Answer__c": "マネージャが所有するアカウント(取引先)およびコンタクト(取引先責任者)に関する活動レポート",
            "isAnswer__c": false,
            "eqQuestion__c": "@eqQuestion__cRef1"
        },
        {
            "attributes": {
                "type": "eqAnswer__c",
                "referenceId": "eqAnswer__cRef4"
            },
            "Answer__c": "マネージャが所有するアカウント(取引先)に関する活動レポート",
            "isAnswer__c": false,
            "eqQuestion__c": "@eqQuestion__cRef1"
        },
        {
            "attributes": {
                "type": "eqAnswer__c",
                "referenceId": "eqAnswer__cRef5"
            },
            "Answer__c": "通貨消込",
            "isAnswer__c": false,
            "eqQuestion__c": "@eqQuestion__cRef2"
        },
        {
            "attributes": {
                "type": "eqAnswer__c",
                "referenceId": "eqAnswer__cRef6"
            },
            "Answer__c": "販売手数料",
            "isAnswer__c": false,
            "eqQuestion__c": "@eqQuestion__cRef2"
        },
        {
            "attributes": {
                "type": "eqAnswer__c",
                "referenceId": "eqAnswer__cRef7"
            },
            "Answer__c": "オーバーレイ・セールス・チームの調整",
            "isAnswer__c": true,
            "eqQuestion__c": "@eqQuestion__cRef2"
        },
        {
            "attributes": {
                "type": "eqAnswer__c",
                "referenceId": "eqAnswer__cRef8"
            },
            "Answer__c": "アカウント(取引先)およびオポチュニティ(商談)のデータ・アクセス・ルール",
            "isAnswer__c": true,
            "eqQuestion__c": "@eqQuestion__cRef2"
        },
        {
            "attributes": {
                "type": "eqAnswer__c",
                "referenceId": "eqAnswer__cRef9"
            },
            "Answer__c": "テリトリへのアカウントの割当",
            "isAnswer__c": true,
            "eqQuestion__c": "@eqQuestion__cRef2"
        },
        {
            "attributes": {
                "type": "eqAnswer__c",
                "referenceId": "eqAnswer__cRef10"
            },
            "Answer__c": "関連する子サポート案件を作成し、その子サポート案件を製品開発チームに割り当てます。",
            "isAnswer__c": false,
            "eqQuestion__c": "@eqQuestion__cRef3"
        },
        {
            "attributes": {
                "type": "eqAnswer__c",
                "referenceId": "eqAnswer__cRef11"
            },
            "Answer__c": "顧客とのプライベート Chatter グループを作成し、主要な個人をグループに招待します。",
            "isAnswer__c": true,
            "eqQuestion__c": "@eqQuestion__cRef3"
        },
        {
            "attributes": {
                "type": "eqAnswer__c",
                "referenceId": "eqAnswer__cRef12"
            },
            "Answer__c": "統合に関連するナレッジ記事のリポジトリを構築し、顧客と共有します。",
            "isAnswer__c": false,
            "eqQuestion__c": "@eqQuestion__cRef3"
        },
        {
            "attributes": {
                "type": "eqAnswer__c",
                "referenceId": "eqAnswer__cRef13"
            },
            "Answer__c": "Chatter ケースフィードを有効にし、製品開発チームのメンバーをケースチームに追加します。",
            "isAnswer__c": false,
            "eqQuestion__c": "@eqQuestion__cRef3"
        },
        {
            "attributes": {
                "type": "eqAnswer__c",
                "referenceId": "eqAnswer__cRef14"
            },
            "Answer__c": "商品と価格表",
            "isAnswer__c": false,
            "eqQuestion__c": "@eqQuestion__cRef4"
        },
        {
            "attributes": {
                "type": "eqAnswer__c",
                "referenceId": "eqAnswer__cRef15"
            },
            "Answer__c": "取引先責任者と納入商品",
            "isAnswer__c": false,
            "eqQuestion__c": "@eqQuestion__cRef4"
        },
        {
            "attributes": {
                "type": "eqAnswer__c",
                "referenceId": "eqAnswer__cRef16"
            },
            "Answer__c": "商談と商品",
            "isAnswer__c": true,
            "eqQuestion__c": "@eqQuestion__cRef4"
        },
        {
            "attributes": {
                "type": "eqAnswer__c",
                "referenceId": "eqAnswer__cRef17"
            },
            "Answer__c": "取引先と商談",
            "isAnswer__c": false,
            "eqQuestion__c": "@eqQuestion__cRef4"
        }
    ]
}